{
    "machine": "alloy_furnace",
    "registryName": "alloy_furnace_diamond",
    "recipeTime": 5,
    "requirements": [
        {
            "type": "modularmachinery:energy",
            "io-type": "input",
            "energyPerTick": 100
        },
        {
            "type": "modularmachinery:item",
            "io-type": "output",
            "item": "mekanism:ControlCircuit",
            "amount": 1
        },
        {
            "type": "modularmachinery:item",
            "io-type": "input",
            "item": "mekanism:EnrichedAlloy",
            "amount": 4
        },
        {
            "type": "modularmachinery:item",
            "io-type": "input",
            "item": "minecraft:redstone",
            "amount": 8
        },
        {
            "type": "modularmachinery:item",
            "io-type": "input",
            "item": "minecraft:emerald",
            "amount": 2
        }
    ]
}
